CHANGES.txt
README.rst
setup.cfg
setup.py
hexagonit/__init__.py
hexagonit.swfheader.egg-info/PKG-INFO
hexagonit.swfheader.egg-info/SOURCES.txt
hexagonit.swfheader.egg-info/dependency_links.txt
hexagonit.swfheader.egg-info/entry_points.txt
hexagonit.swfheader.egg-info/namespace_packages.txt
hexagonit.swfheader.egg-info/not-zip-safe
hexagonit.swfheader.egg-info/requires.txt
hexagonit.swfheader.egg-info/top_level.txt
hexagonit/swfheader/__init__.py
hexagonit/swfheader/test.swf
hexagonit/swfheader/tests.py