Metadata-Version: 1.1
Name: hexagonit.swfheader
Version: 1.2
Summary: SWF metadata parser
Home-page: UNKNOWN
Author: Kai Lautaportti
Author-email: kai.lautaportti@hexagonit.fi
License: GPL
Keywords: SWF
Platform: UNKNOWN
Classifier: Programming Language :: Python
Classifier: Intended Audience :: Developers
Classifier: License :: OSI Approved :: GNU General Public License (GPL)
Classifier: Topic :: Multimedia
Classifier: Topic :: Software Development :: Libraries :: Python Modules
